cocotask/__init__.py
cocotask/base_consumer.py
cocotask/base_producer.py
cocotask/base_worker.py
cocotask/consumer_manager.py
cocotask/logger.py
cocotask/producer_manager.py
cocotask/taskrunner.py
cocotask/kafka/__init__.py
cocotask/kafka/kafka_consumer.py
cocotask/kafka/kafka_producer.py
cocotask/rabbitmq/__init__.py
cocotask/rabbitmq/common.py
cocotask/rabbitmq/rmq_consumer.py
cocotask/rabbitmq/rmq_producer.py
cocotask/redis/__init__.py
cocotask/redis/redis_consumer.py
cocotask/redis/redis_producer.py
cocotask-0.2.1.1.dist-info/DESCRIPTION.rst
cocotask-0.2.1.1.dist-info/LICENSE.txt
cocotask-0.2.1.1.dist-info/METADATA
cocotask-0.2.1.1.dist-info/RECORD
cocotask-0.2.1.1.dist-info/WHEEL
cocotask-0.2.1.1.dist-info/entry_points.txt
cocotask-0.2.1.1.dist-info/metadata.json
cocotask-0.2.1.1.dist-info/top_level.txt
