Metadata-Version: 2.0
Name: cocotask
Version: 0.2.1.1
Summary: An unified framework to build task queue on Rabbitmq | Kafka | Redis
Home-page: https://github.com/likexx/cocotask
Author: Like Zhang
Author-email: zlike@yahoo.com
License: MIT
Keywords: task message queue MQ Pika kafka-python rabbitmq kafka redis rmq producer consumer celery
Platform: UNKNOWN
Requires-Dist: jsmin
Requires-Dist: kafka-python
Requires-Dist: pika
Requires-Dist: redis
